<?xml version="1.0" ?>
<PyBrain>
	<Network class="pybrain.structure.networks.feedforward.FeedForwardNetwork" name="FeedForwardNetwork-8">
		<name val="'FeedForwardNetwork-8'"/>
		<Modules>
			<LinearLayer class="pybrain.structure.modules.linearlayer.LinearLayer" inmodule="True" name="in">
				<dim val="7"/>
				<name val="'in'"/>
			</LinearLayer>
			<LinearLayer class="pybrain.structure.modules.linearlayer.LinearLayer" name="out" outmodule="True">
				<dim val="2"/>
				<name val="'out'"/>
			</LinearLayer>
			<BiasUnit class="pybrain.structure.modules.biasunit.BiasUnit" name="bias">
				<name val="'bias'"/>
			</BiasUnit>
			<SigmoidLayer class="pybrain.structure.modules.sigmoidlayer.SigmoidLayer" name="hidden0">
				<dim val="20"/>
				<name val="'hidden0'"/>
			</SigmoidLayer>
		</Modules>
		<Connections>
			<FullConnection class="pybrain.structure.connections.full.FullConnection" name="FullConnection-4">
				<inmod val="bias"/>
				<outmod val="out"/>
				<Parameters>[0.10276498083286506, 1.0227998441040786]</Parameters>
			</FullConnection>
			<FullConnection class="pybrain.structure.connections.full.FullConnection" name="FullConnection-5">
				<inmod val="bias"/>
				<outmod val="hidden0"/>
				<Parameters>[-1.7639221305392794, -1.6783038244292208, -0.32687319702695933, 1.4707230754920204, 0.35391652655095768, -0.83908346574438841, 0.81714456584979778, -0.5627398073028983, -1.3672296796818866, 0.33429733289011521, 0.15376166009655601, 1.1552968587952619, -0.55249207737341932, -1.5248347494111085, -6.0506714456665618, -1.5563802903249782, 0.18428649131834585, 0.20251710690813038, -0.73890183947738153, 2.1823452382288027]</Parameters>
			</FullConnection>
			<FullConnection class="pybrain.structure.connections.full.FullConnection" name="FullConnection-7">
				<inmod val="in"/>
				<outmod val="hidden0"/>
				<Parameters>[-1.5976042003441693, -0.19858410346592284, 0.44727467839447271, -2.7594837289150607, -0.32467057294589785, 0.014480624294000644, -1.572807354569949, -0.76769964576500693, -1.7465963177331123, 1.5505438246170666, -1.0500153493226063, 1.4945980464661388, -0.31335382475910351, -0.42188769554834765, -0.76930804957883314, -1.5604136732498521, 0.090289694743249826, -1.0333610063326752, -1.1926802761649615, -0.059544958806968917, 0.55882729971107437, -1.8824775187496332, -2.6743391260694263, 0.19000494741824692, -0.41601198717745752, 1.5530722398861048, -2.2732996528368248, 0.42811255801300174, -1.6337935830991335, 1.1255428157107505, -1.9172655746871754, 0.19443336949308995, -0.43330213379832572, 0.16789574568834942, -0.58237021309927772, -1.4335654365059702, 0.061474399661404625, -1.2677151137373754, 0.81697346261818371, -0.074442180679723274, 0.47846930116256858, -0.57824035662151818, -1.285315612836065, 0.056704555979750396, 0.19641348187624971, -0.15631082696749898, -0.41915612625186655, -0.98027268145933122, -2.5196870242704175, -0.35497440683365344, -0.35234307543685162, -0.59387188578415229, 0.024028509473583315, 0.31969450260962412, 1.4918113076385193, -1.4186185079855342, -0.24654708502588349, -0.91644156808429222, -2.024305460420091, 1.3455450158570281, -0.74346817343188198, -0.71961796046575477, -0.054960797124867018, -1.3682516137560228, -2.1671729166270861, -0.55465375110164439, 0.25661226990217006, -0.23460143282990989, -0.34419674414478391, 0.23320298586943428, -0.29205443158540995, -1.0468338820146417, -1.0885743651996267, -1.9315691402349819, 0.86332296048774504, 0.19113590925896026, -1.4047854150350252, -3.3406471326902731, -1.0344264129385452, 0.54171722457445137, 0.16606394700787455, -1.3614767370501297, 0.28779695777098369, -2.0901515288706118, -2.1492911897533684, -0.59320210420515995, 2.2960717872081347, -1.9030500432469202, -2.2315504278055256, -3.0891850450298235, -2.9961632613936997, -0.98397777031959788, 1.1413510042556738, -1.4261705347511973, 0.064682701664736553, -1.7698850904235013, 1.3001324876992899, -1.1486753577518085, 1.071136077461869, 0.77835659354813846, 2.2925392550565094, -0.042680625593942756, 0.022682354070825618, 0.64938938376991306, -4.6944186821039837, -1.7881006199850944, -0.10368304469709093, 0.3043061096577192, -0.82860501131343423, 0.7610906526615453, 0.99969160881694297, 0.1938222697186131, -0.69819615438091298, -1.489940434533624, -0.58989683857714059, -1.2124353871082452, -0.57251552696570274, 0.61420176237388058, 0.25294234746497096, 0.051772219607875307, -1.3465576382012541, 0.9077328616151088, -0.96578896485603893, -0.24945019102123792, -1.2951131976503054, -2.6246174400583238, 0.90444859738309857, -0.7505710545305786, -1.7146704447070178, 0.53610743956119267, -1.1037866900332558, 0.207706959503515, -0.60956576978066213, 0.87887627213531783, -2.8578469266704123, -1.5068620150582048, 2.47525167711663, -0.28456659946814394, -0.87787408790379129, 3.2200250045846661]</Parameters>
			</FullConnection>
			<FullConnection class="pybrain.structure.connections.full.FullConnection" name="FullConnection-6">
				<inmod val="hidden0"/>
				<outmod val="out"/>
				<Parameters>[-0.33943152782845626, -1.1133689059256831, 0.76492735297377734, 0.30752333511966301, -0.41892896628775506, 0.23971778512551931, -0.24315872555215137, -0.81391352817495888, -1.0820259188935313, -1.165923547985166, -0.097993928819729292, 0.059129213235317953, -0.51144223371708353, -0.76429191200218161, 0.93819641612838378, -0.83020054848203528, 0.97429012585578689, -0.45513274107829443, 0.21115905801412269, -0.032964410923497008, 0.30634534456694368, -0.43969566932810522, -0.56481477799169189, 1.4642471143968021, -0.39529278235548199, 0.20606495253755774, -0.8126082563596797, -0.76546814212980652, 0.4024660028202941, 0.72372221723644892, -0.53704527909798694, 1.201725884397735, -0.94565547449127174, 0.21221370310242466, 0.19658680048894606, 0.024663298699734944, -0.68940544521003388, -0.60870705687504723, -0.81567600817523589, -0.98554585700718123]</Parameters>
			</FullConnection>
		</Connections>
	</Network>
</PyBrain>
